
[
  { "key": "AUD", "text": "AUD", "value": "AUD" },
  { "key": "BGN", "text": "BGN", "value": "BGN" },
  { "key": "BRL", "text": "BRL", "value": "BRL" },
  { "key": "CAD", "text": "CAD", "value": "CAD" },
  { "key": "CHF", "text": "CHF", "value": "CHF" },
  { "key": "CNY", "text": "CNY", "value": "CNY" },
  { "key": "CZK", "text": "CZK", "value": "CZK" },
  { "key": "DKK", "text": "DKK", "value": "DKK" },
  { "key": "GBP", "text": "GBP", "value": "GBP" },
  { "key": "HKD", "text": "HKD", "value": "HKD" },
  { "key": "HRK", "text": "HRK", "value": "HRK" },
  { "key": "HUF", "text": "HUF", "value": "HUF" },
  { "key": "IDR", "text": "IDR", "value": "IDR" },
  { "key": "ILS", "text": "ILS", "value": "ILS" },
  { "key": "INR", "text": "INR", "value": "INR" },
  { "key": "ISK", "text": "ISK", "value": "ISK" },
  { "key": "JPY", "text": "JPY", "value": "JPY" },
  { "key": "KRW", "text": "KRW", "value": "KRW" },
  { "key": "MXN", "text": "MXN", "value": "MXN" },
  { "key": "MYR", "text": "MYR", "value": "MYR" },
  { "key": "NOK", "text": "NOK", "value": "NOK" },
  { "key": "NZD", "text": "NZD", "value": "NZD" },
  { "key": "PHP", "text": "PHP", "value": "PHP" },
  { "key": "PLN", "text": "PLN", "value": "PLN" },
  { "key": "RON", "text": "RON", "value": "RON" },
  { "key": "RUB", "text": "RUB", "value": "RUB" },
  { "key": "SEK", "text": "SEK", "value": "SEK" },
  { "key": "SGD", "text": "SGD", "value": "SGD" },
  { "key": "THB", "text": "THB", "value": "THB" },
  { "key": "TRY", "text": "TRY", "value": "TRY" },
  { "key": "USD", "text": "USD", "value": "USD" },
  { "key": "ZAR", "text": "ZAR", "value": "ZAR" }
]
